changeln/__init__.py
changeln/__main__.py
changeln/src/__init__.py
changeln/src/features/__init__.py
changeln/src/features/group_make.py
changeln/src/support/__init__.py
changeln/src/support/conf.py
changeln/src/support/dependency.py
changeln/src/support/helper.py
changeln/src/support/output.py
changeln/src/support/parse_git.py
changeln/src/support/texts.py
changeln/src/support/data/__init__.py
changeln/src/support/data/config.py
changeln/src/support/data/template.py
changeln-2.0.2.0.dist-info/LICENSE
changeln-2.0.2.0.dist-info/METADATA
changeln-2.0.2.0.dist-info/WHEEL
changeln-2.0.2.0.dist-info/entry_points.txt
changeln-2.0.2.0.dist-info/top_level.txt
changeln-2.0.2.0.dist-info/RECORD
