Metadata-Version: 2.1
Name: changeln
Version: 2.0.2.0
Summary: The application allows you to generate CHANGELOG files based on Git tags.
Home-page: https://github.com/keygenqt/changeln
Author: Vitaliy Zarubin
Author-email: keygenqt@gmail.com
Requires-Python: >=3.8.2
License-File: LICENSE
Requires-Dist: click >=8.1.7
Requires-Dist: pyYaml >=6.0.1
Requires-Dist: Mako >=1.3.2
Requires-Dist: Markdown >=3.5.2
Requires-Dist: weasyprint >=61.1
Requires-Dist: cffi >=1.16.0
Requires-Dist: GitPython >=3.1.41
Requires-Dist: natsort >=8.4.0
Requires-Dist: beautifulsoup4 >=4.12.3
